listdirs/__init__.py
listdirs/cli.py
listdirs-0.1.0.dist-info/METADATA
listdirs-0.1.0.dist-info/WHEEL
listdirs-0.1.0.dist-info/entry_points.txt
listdirs-0.1.0.dist-info/top_level.txt
listdirs-0.1.0.dist-info/RECORD
