Metadata-Version: 2.1
Name: listdirs
Version: 0.1.0
Summary: Add your description here
Requires-Python: >=3.13
Requires-Dist: typer>=0.15.1
